[
  {
    "title": "Sololearn",
    "description": "This is the place where I started. Learned about HTML, CSS"
  },
  {
    "title": "Klaipėdos paslaugų ir verslo mokykla",
    "description": "In this place I learned about CSS, JS, PHP, MySQL, Python"
  },
  {
    "title": "Erasmus +",
    "description": "This time I went to the Poland for 2 weeks and learned about Figma and Wordpress."
  },
  {
    "title": "Udemy.com",
    "description": "A bunch of courses about various topics, like Python, advanced JavaScript, Java, React, Node.js and more..."
  }
]
